saveme/__init__.py
saveme/cli.py
saveme/ns-icon.icns
saveme/helpers/__init__.py
saveme/helpers/config.py
saveme/helpers/vault.py
saveme/templates/__init__.py
saveme/templates/launchagent.pt
saveme-0.0.3.dist-info/LICENSE
saveme-0.0.3.dist-info/METADATA
saveme-0.0.3.dist-info/WHEEL
saveme-0.0.3.dist-info/entry_points.txt
saveme-0.0.3.dist-info/top_level.txt
saveme-0.0.3.dist-info/RECORD
