Metadata-Version: 2.1
Name: saveme
Version: 0.0.3
Summary: OSX Menu Bar for AWS-Vault Metadata Server (via launchctl)
Home-page: UNKNOWN
Author: Marcus Young
Author-email: myoung34@my.apsu.edu
License: UNKNOWN
Platform: UNKNOWN
Requires-Dist: altgraph (==0.17)
Requires-Dist: chameleon (==3.9.0)
Requires-Dist: click (==7.1.2)
Requires-Dist: macholib (==1.14)
Requires-Dist: modulegraph (==0.18)
Requires-Dist: py2app (==0.23)
Requires-Dist: pyobjc-core (==7.1)
Requires-Dist: pyobjc-framework-cocoa (==7.1)
Requires-Dist: rumps (==0.3.0)
Requires-Dist: shellescape (==3.8.1)
